pi_internet_webthing/__init__.py
pi_internet_webthing/app.py
pi_internet_webthing/connectivity_monitor_webthing.py
pi_internet_webthing/internet_multiple_webthing.py
pi_internet_webthing/speedtest_monitor_webthing.py
pi_internet_webthing-0.0.26.dist-info/LICENSE
pi_internet_webthing-0.0.26.dist-info/METADATA
pi_internet_webthing-0.0.26.dist-info/WHEEL
pi_internet_webthing-0.0.26.dist-info/entry_points.txt
pi_internet_webthing-0.0.26.dist-info/top_level.txt
pi_internet_webthing-0.0.26.dist-info/RECORD
