Metadata-Version: 2.1
Name: pi-internet-webthing
Version: 0.0.26
Summary: A web connected local internet speed and connectivity monitor
Home-page: https://github.com/grro/pi_internet_webthing
Author: Gregor Roth
Author-email: gregor.roth@web.de
License: MIT
Keywords: webthings,home automation,speedtest,internet,local,raspberry,pi
Platform: UNKNOWN
Classifier: Programming Language :: Python :: 3
Classifier: License :: OSI Approved :: Apache Software License
Classifier: Operating System :: OS Independent
Classifier: Development Status :: 3 - Alpha
Requires-Dist: webthing
Requires-Dist: speedtest-cli
